ultrafast_client-0.2.3.dist-info/METADATA
ultrafast_client-0.2.3.dist-info/WHEEL
ultrafast_client-0.2.3.dist-info/licenses/LICENSE
ultrafast_client.libs/libcom_err-2abe824b.so.2
ultrafast_client.libs/libcrypto-d3570994.so.10
ultrafast_client.libs/libgssapi_krb5-497db0c6.so.2
ultrafast_client.libs/libk5crypto-b1f99d5c.so.3
ultrafast_client.libs/libkeyutils-dfe70bd6.so.1
ultrafast_client.libs/libkrb5-fcafa220.so.3
ultrafast_client.libs/libkrb5support-d0bcff84.so.0
ultrafast_client.libs/libpcre-9513aab5.so.1
ultrafast_client.libs/libselinux-0922c95c.so.1
ultrafast_client.libs/libssl-cd1d6220.so.10
ultrafast_client/__init__.py
ultrafast_client/_ultrafast_client.abi3.so
ultrafast_client/py.typed
ultrafast_client-0.2.3.dist-info/RECORD
