Metadata-Version: 2.4
Name: ultrafast-client
Version: 0.2.3
Classifier: Development Status :: 4 - Beta
Classifier: Intended Audience :: Developers
Classifier: License :: OSI Approved :: Apache Software License
Classifier: Operating System :: OS Independent
Classifier: Programming Language :: Python :: 3
Classifier: Programming Language :: Python :: 3.8
Classifier: Programming Language :: Python :: 3.9
Classifier: Programming Language :: Python :: 3.10
Classifier: Programming Language :: Python :: 3.11
Classifier: Programming Language :: Python :: 3.12
Classifier: Programming Language :: Rust
Classifier: Topic :: Internet :: WWW/HTTP
Classifier: Topic :: Software Development :: Libraries :: Python Modules
Classifier: Topic :: System :: Networking
Requires-Dist: typing-extensions>=4.0.0 ; python_full_version < '3.10'
Requires-Dist: pytest>=7.0.0 ; extra == 'dev'
Requires-Dist: pytest-asyncio>=0.21.0 ; extra == 'dev'
Requires-Dist: pytest-benchmark>=4.0.0 ; extra == 'dev'
Requires-Dist: black>=23.0.0 ; extra == 'dev'
Requires-Dist: isort>=5.12.0 ; extra == 'dev'
Requires-Dist: mypy>=1.0.0 ; extra == 'dev'
Requires-Dist: ruff>=0.1.0 ; extra == 'dev'
Requires-Dist: pre-commit>=3.0.0 ; extra == 'dev'
Requires-Dist: httpx>=0.25.0 ; extra == 'dev'
Requires-Dist: aiohttp>=3.8.0 ; extra == 'dev'
Requires-Dist: requests>=2.28.0 ; extra == 'dev'
Requires-Dist: pytest>=7.0.0 ; extra == 'test'
Requires-Dist: pytest-asyncio>=0.21.0 ; extra == 'test'
Requires-Dist: pytest-benchmark>=4.0.0 ; extra == 'test'
Requires-Dist: httpx>=0.25.0 ; extra == 'test'
Requires-Dist: aiohttp>=3.8.0 ; extra == 'test'
Requires-Dist: requests>=2.28.0 ; extra == 'test'
Requires-Dist: sphinx>=6.0.0 ; extra == 'docs'
Requires-Dist: sphinx-rtd-theme>=1.3.0 ; extra == 'docs'
Requires-Dist: myst-parser>=2.0.0 ; extra == 'docs'
Requires-Dist: sphinx-autodoc-typehints>=1.24.0 ; extra == 'docs'
Requires-Dist: httpx>=0.25.0 ; extra == 'benchmark'
Requires-Dist: aiohttp>=3.8.0 ; extra == 'benchmark'
Requires-Dist: requests>=2.28.0 ; extra == 'benchmark'
Requires-Dist: matplotlib>=3.6.0 ; extra == 'benchmark'
Requires-Dist: pandas>=1.5.0 ; extra == 'benchmark'
Requires-Dist: psutil>=5.9.0 ; extra == 'benchmark'
Provides-Extra: dev
Provides-Extra: test
Provides-Extra: docs
Provides-Extra: benchmark
License-File: LICENSE
Summary: A blazingly fast HTTP client for Python, built with Rust and Tokio
Keywords: http,client,async,rust,performance
Home-Page: https://github.com/techgopal/ultrafast-client
Author: UltraFast Team <techgopal@example.com>
Author-email: UltraFast Team <techgopal@example.com>
License: Apache-2.0
Requires-Python: >=3.8
Project-URL: Bug Reports, https://github.com/techgopal/ultrafast-client/issues
Project-URL: Source, https://github.com/techgopal/ultrafast-client
Project-URL: Documentation, https://ultrafast-client.readthedocs.io
Project-URL: Changelog, https://github.com/techgopal/ultrafast-client/blob/main/CHANGELOG.md
Project-URL: Funding, https://github.com/sponsors/techgopal
Project-URL: Release Notes, https://github.com/techgopal/ultrafast-client/releases
